odoo/addons/account_move_line_mrp_info/README.rst
odoo/addons/account_move_line_mrp_info/__init__.py
odoo/addons/account_move_line_mrp_info/__manifest__.py
odoo/addons/account_move_line_mrp_info/hooks.py
odoo/addons/account_move_line_mrp_info/i18n/account_move_line_mrp_info.pot
odoo/addons/account_move_line_mrp_info/models/__init__.py
odoo/addons/account_move_line_mrp_info/models/account_move_line.py
odoo/addons/account_move_line_mrp_info/models/mrp_production.py
odoo/addons/account_move_line_mrp_info/readme/CONTRIBUTORS.rst
odoo/addons/account_move_line_mrp_info/readme/DESCRIPTION.rst
odoo/addons/account_move_line_mrp_info/readme/USAGE.rst
odoo/addons/account_move_line_mrp_info/security/ir.model.access.csv
odoo/addons/account_move_line_mrp_info/static/description/icon.png
odoo/addons/account_move_line_mrp_info/static/description/index.html
odoo/addons/account_move_line_mrp_info/tests/__init__.py
odoo/addons/account_move_line_mrp_info/tests/test_mrp_journal_items.py
odoo/addons/account_move_line_mrp_info/views/account_move_line_view.xml
odoo/addons/account_move_line_mrp_info/views/mrp_production_view.xml
odoo14_addon_account_move_line_mrp_info-14.0.1.1.0.dist-info/METADATA
odoo14_addon_account_move_line_mrp_info-14.0.1.1.0.dist-info/WHEEL
odoo14_addon_account_move_line_mrp_info-14.0.1.1.0.dist-info/top_level.txt
odoo14_addon_account_move_line_mrp_info-14.0.1.1.0.dist-info/RECORD
