Metadata-Version: 2.1
Name: odoo14-addon-account-move-line-mrp-info
Version: 14.0.1.1.0
Summary: Account Move Line Mrp Info
Home-page: https://github.com/OCA/manufacture
Author: ForgeFlow,Odoo Community Association (OCA)
Author-email: support@odoo-community.org
License: AGPL-3
Platform: UNKNOWN
Classifier: Programming Language :: Python
Classifier: Framework :: Odoo
Classifier: Framework :: Odoo :: 14.0
Classifier: License :: OSI Approved :: GNU Affero General Public License v3
Requires-Python: >=3.6
Requires-Dist: odoo14-addon-account-move-line-stock-info
Requires-Dist: odoo (<14.1dev,>=14.0a)
